{
  "calendars": {
    "2026": [
      {
        "date": "2026-01-06",
        "time": "24时",
        "note": "第一次调价"
      },
      {
        "date": "2026-01-20",
        "time": "24时",
        "note": "第二次调价"
      },
      {
        "date": "2026-02-03",
        "time": "24时",
        "note": "第三次调价"
      },
      {
        "date": "2026-02-24",
        "time": "24时",
        "note": "第四次调价"
      },
      {
        "date": "2026-03-09",
        "time": "24时",
        "note": "第五次调价"
      },
      {
        "date": "2026-03-23",
        "time": "24时",
        "note": "第六次调价"
      },
      {
        "date": "2026-04-07",
        "time": "24时",
        "note": "第七次调价"
      },
      {
        "date": "2026-04-21",
        "time": "24时",
        "note": "第八次调价"
      },
      {
        "date": "2026-05-08",
        "time": "24时",
        "note": "第九次调价"
      },
      {
        "date": "2026-05-21",
        "time": "24时",
        "note": "第十次调价"
      },
      {
        "date": "2026-06-04",
        "time": "24时",
        "note": "第十一次调价"
      },
      {
        "date": "2026-06-18",
        "time": "24时",
        "note": "第十二次调价"
      },
      {
        "date": "2026-07-03",
        "time": "24时",
        "note": "第十三次调价"
      },
      {
        "date": "2026-07-17",
        "time": "24时",
        "note": "第十四次调价"
      },
      {
        "date": "2026-07-31",
        "time": "24时",
        "note": "第十五次调价"
      },
      {
        "date": "2026-08-14",
        "time": "24时",
        "note": "第十六次调价"
      },
      {
        "date": "2026-08-28",
        "time": "24时",
        "note": "第十七次调价"
      },
      {
        "date": "2026-09-11",
        "time": "24时",
        "note": "第十八次调价"
      },
      {
        "date": "2026-09-24",
        "time": "24时",
        "note": "第十九次调价"
      },
      {
        "date": "2026-10-15",
        "time": "24时",
        "note": "第二十次调价"
      },
      {
        "date": "2026-10-29",
        "time": "24时",
        "note": "第二十一次调价"
      },
      {
        "date": "2026-11-12",
        "time": "24时",
        "note": "第二十二次调价"
      },
      {
        "date": "2026-11-26",
        "time": "24时",
        "note": "第二十三次调价"
      },
      {
        "date": "2026-12-10",
        "time": "24时",
        "note": "第二十四次调价"
      },
      {
        "date": "2026-12-24",
        "time": "24时",
        "note": "第二十五次调价"
      }
    ]
  },
  "metadata": {
    "version": "1.0.0",
    "lastUpdate": "2026-03-04T00:00:00.000Z",
    "source": "国家发改委官方调价日历",
    "description": "国内成品油调价日历数据，支持多年度查询"
  }
}
